factverifai/__init__.py
factverifai/core.py
factverifai-0.1.8.dist-info/METADATA
factverifai-0.1.8.dist-info/WHEEL
factverifai-0.1.8.dist-info/top_level.txt
factverifai-0.1.8.dist-info/RECORD
