Metadata-Version: 2.4
Name: factverifai
Version: 0.1.8
Summary: AI-powered fact-checking Python library
Author-email: Your Name <iliescuaf@gmail.com>
Project-URL: Homepage, https://github.com/a-i-flo/factverifai
Requires-Python: >=3.13
Requires-Dist: ipykernel
Requires-Dist: openai
Requires-Dist: ollama
Requires-Dist: exa_py
Requires-Dist: python-dotenv
Requires-Dist: langchain
Requires-Dist: langgraph
Requires-Dist: langchain_community
Requires-Dist: langchain-ollama
Requires-Dist: langchain-exa
Requires-Dist: requests
